{
    "id": "ods18",
    "titulo": "Igualdade Racial, Combate ao Racismo e Promoção da Equidade Étnico-Racial",
    "descricao": "O ODS 18 é uma iniciativa brasileira que complementa os 17 ODS globais da ONU com um objetivo específico voltado para a promoção da igualdade racial, combate ao racismo estrutural e valorização da diversidade étnico-racial. Esta adição reconhece que o enfrentamento das desigualdades raciais é fundamental para o desenvolvimento sustentável no contexto brasileiro.",
    "cor_primaria": "#6F1D78",
    "cor_secundaria": "rgba(111, 29, 120, 0.2)",
    "meta_nacional": "Eliminar todas as formas de discriminação racial e promover a equidade étnico-racial em todos os setores da sociedade brasileira até 2030.",
    "data_atualizacao": "2025-04-13T12:00:00Z",
    "indicadores": {
        "acesso_ensino_superior": {
            "id": "acesso_ensino_superior",
            "titulo": "Acesso ao Ensino Superior para pessoas negras",
            "descricao": "Percentual de estudantes negros (pretos e pardos) matriculados no ensino superior.",
            "unidade": "%",
            "tipo": "percentual",
            "fonte": "INEP/IBGE",
            "dados": {
                "valor": 54.8,
                "ano": 2024
            },
            "meta_2030": 65.0,
            "historico": [
                { "ano": 2018, "valor": 40.2 },
                { "ano": 2019, "valor": 43.5 },
                { "ano": 2020, "valor": 46.8 },
                { "ano": 2021, "valor": 48.2 },
                { "ano": 2022, "valor": 50.4 },
                { "ano": 2023, "valor": 52.6 },
                { "ano": 2024, "valor": 54.8 }
            ]
        },
        "desigualdade_salarial": {
            "id": "desigualdade_salarial",
            "titulo": "Desigualdade Salarial entre pessoas brancas e negras",
            "descricao": "Razão entre o rendimento médio de pessoas brancas e pessoas negras (pretas e pardas). Quanto mais próximo de 1, menor a desigualdade.",
            "unidade": "razão",
            "tipo": "numerica",
            "fonte": "IBGE - PNAD Contínua",
            "dados": {
                "valor": 1.58,
                "ano": 2024
            },
            "meta_2030": 1.10,
            "historico": [
                { "ano": 2017, "valor": 2.10 },
                { "ano": 2018, "valor": 1.95 },
                { "ano": 2019, "valor": 1.85 },
                { "ano": 2020, "valor": 1.82 },
                { "ano": 2021, "valor": 1.75 },
                { "ano": 2022, "valor": 1.68 },
                { "ano": 2023, "valor": 1.62 },
                { "ano": 2024, "valor": 1.58 }
            ]
        },
        "representatividade_lideranca": {
            "id": "representatividade_lideranca",
            "titulo": "Representatividade em Cargos de Liderança",
            "descricao": "Percentual de pessoas negras (pretas e pardas) em cargos de liderança no setor público e privado.",
            "unidade": "%",
            "tipo": "percentual",
            "fonte": "IBGE / Observatório da Diversidade",
            "dados": {
                "valor": 32.5,
                "ano": 2024
            },
            "meta_2030": 55.0,
            "historico": [
                { "ano": 2018, "valor": 22.8 },
                { "ano": 2019, "valor": 24.3 },
                { "ano": 2020, "valor": 25.7 },
                { "ano": 2021, "valor": 27.5 },
                { "ano": 2022, "valor": 29.2 },
                { "ano": 2023, "valor": 31.0 },
                { "ano": 2024, "valor": 32.5 }
            ]
        },
        "reconhecimento_territorios": {
            "id": "reconhecimento_territorios",
            "titulo": "Reconhecimento de Territórios Tradicionais",
            "descricao": "Percentual de territórios quilombolas e comunidades tradicionais com titulação definitiva.",
            "unidade": "%",
            "tipo": "percentual",
            "fonte": "INCRA / Fundação Palmares",
            "dados": {
                "valor": 31.2,
                "ano": 2024
            },
            "meta_2030": 100.0,
            "historico": [
                { "ano": 2017, "valor": 12.8 },
                { "ano": 2018, "valor": 14.5 },
                { "ano": 2019, "valor": 17.3 },
                { "ano": 2020, "valor": 19.8 },
                { "ano": 2021, "valor": 23.4 },
                { "ano": 2022, "valor": 26.5 },
                { "ano": 2023, "valor": 28.9 },
                { "ano": 2024, "valor": 31.2 }
            ]
        }
    }
}